{
    "backend": "django",
    "db_name": "",
    "db_pass": "",
    "db_type": "sqlite",
    "db_user": "",
    "dbms": "1",
    "description": "generated product",
    "design": "material-kit",
    "docker": "1",
    "err_code": 0,
    "frontend": "",
    "heroku": "0",
    "pattern": "mvc",
    "pro": "0",
    "task_id": "930e02f4-697e-4236-a3d5-f53c0baf028a",
    "task_info": "Upload Sources [0%] - 366 files",
    "task_output": "930e02f4-697e-4236-a3d5-f53c0baf028a.zip",
    "task_result": "SUCCESS",
    "task_state": "RUNNING",
    "task_ts_end": "2024-03-03-19-10-05",
    "task_ts_start": "2024-03-03-19-10-01"
}